<?xml version="1.0" encoding="utf-8"?>
<resources>
	<version>1</version>
	<category title="New" />
	<item drawable="_7_minute_workout" />
	<item drawable="abbanoa" />
	<item drawable="acea_waidy_wow" />
	<item drawable="adaptive_you_icon_pack" />
	<item drawable="all_nippon_airways" />
	<item drawable="amazon_pay_for_bussiness" />
	<item drawable="ambitionbox" />
	<item drawable="ami_ven" />
	<item drawable="ampereflow" />
	<item drawable="ana_mileage_club" />
	<item drawable="androeed" />
	<item drawable="apcoa_flow" />
	<item drawable="appkiller" />
	<item drawable="appsheet" />
	<item drawable="arc_search" />
	<item drawable="avant" />
	<item drawable="avant_money" />
	<item drawable="aves" />
	<item drawable="avg_protection" />
	<item drawable="ays" />
	<item drawable="balatro" />
	<item drawable="bankwest" />
	<item drawable="bdo_pay" />
	<item drawable="beautyplus" />
	<item drawable="bershka" />
	<item drawable="bil_i_oslo" />
	<item drawable="bitget_wallet" />
	<item drawable="bitvavo" />
	<item drawable="ble_radar" />
	<item drawable="blockit" />
	<item drawable="blokk" />
	<item drawable="bondex" />
	<item drawable="bookviewer" />
	<item drawable="borealis" />
	<item drawable="brother_print_service_plugin" />
	<item drawable="bubble_translate" />
	<item drawable="bulder" />
	<item drawable="calendar_tuta_1" />
	<item drawable="calendar_tuta_10" />
	<item drawable="calendar_tuta_11" />
	<item drawable="calendar_tuta_12" />
	<item drawable="calendar_tuta_13" />
	<item drawable="calendar_tuta_14" />
	<item drawable="calendar_tuta_15" />
	<item drawable="calendar_tuta_16" />
	<item drawable="calendar_tuta_17" />
	<item drawable="calendar_tuta_18" />
	<item drawable="calendar_tuta_19" />
	<item drawable="calendar_tuta_2" />
	<item drawable="calendar_tuta_20" />
	<item drawable="calendar_tuta_21" />
	<item drawable="calendar_tuta_22" />
	<item drawable="calendar_tuta_23" />
	<item drawable="calendar_tuta_24" />
	<item drawable="calendar_tuta_25" />
	<item drawable="calendar_tuta_26" />
	<item drawable="calendar_tuta_27" />
	<item drawable="calendar_tuta_28" />
	<item drawable="calendar_tuta_29" />
	<item drawable="calendar_tuta_3" />
	<item drawable="calendar_tuta_30" />
	<item drawable="calendar_tuta_31" />
	<item drawable="calendar_tuta_4" />
	<item drawable="calendar_tuta_5" />
	<item drawable="calendar_tuta_6" />
	<item drawable="calendar_tuta_7" />
	<item drawable="calendar_tuta_8" />
	<item drawable="calendar_tuta_9" />
	<item drawable="carpay" />
	<item drawable="chacoco" />
	<item drawable="chacoco_alt" />
	<item drawable="chaton_ai" />
	<item drawable="chmate" />
	<item drawable="cineplex" />
	<item drawable="citrix_workspace" />
	<item drawable="claro_games" />
	<item drawable="claro_shop" />
	<item drawable="coding_c" />
	<item drawable="coding_keyboard" />
	<item drawable="collectr" />
	<item drawable="cora" />
	<item drawable="cowrywise" />
	<item drawable="creators_app" />
	<item drawable="crystal_para_samsung_internet" />
	<item drawable="detran_df" />
	<item drawable="digiskills_lms" />
	<item drawable="digital_clock" />
	<item drawable="digital_clock_alt" />
	<item drawable="dmart_ready" />
	<item drawable="dynaudio" />
	<item drawable="easee" />
	<item drawable="easy_fast" />
	<item drawable="ebpocket_lite" />
	<item drawable="edpuzzle" />
	<item drawable="electrodoc_pro" />
	<item drawable="electroverse" />
	<item drawable="f1_play" />
	<item drawable="fakespot" />
	<item drawable="financial_times" />
	<item drawable="finanzen_net_zero" />
	<item drawable="flashcards" />
	<item drawable="flat_square_icon_pack" />
	<item drawable="flip_clock" />
	<item drawable="flutter" />
	<item drawable="fossify_calculator" />
	<item drawable="gate_io" />
	<item drawable="gitbook" />
	<item drawable="gmo_town_wifi" />
	<item drawable="go_and_big_c" />
	<item drawable="gruppo_san_donato" />
	<item drawable="hannanmaxig" />
	<item drawable="hearoes" />
	<item drawable="homey" />
	<item drawable="housesigma" />
	<item drawable="icon_changer_2" />
	<item drawable="iegeek_cam" />
	<item drawable="illuminance_lux_light_meter" />
	<item drawable="itr_ais" />
	<item drawable="jd_sports" />
	<item drawable="jiofinance" />
	<item drawable="jmdict_droid" />
	<item drawable="jr" />
	<item drawable="kagawabank" />
	<item drawable="kagi_search" />
	<item drawable="kinestop" />
	<item drawable="kiwi_upi" />
	<item drawable="kron" />
	<item drawable="lawson" />
	<item drawable="level_supermind" />
	<item drawable="light_eq" />
	<item drawable="lumina_walls" />
	<item drawable="marks_and_spencer" />
	<item drawable="metrozone" />
	<item drawable="mico" />
	<item drawable="microsoft_365_admin" />
	<item drawable="microsoft_advertising" />
	<item drawable="microsoft_dynamics_365_remote_assist" />
	<item drawable="microsoft_finance_and_operations" />
	<item drawable="microsoft_power_automate" />
	<item drawable="moonpay" />
	<item drawable="moscow_transport" />
	<item drawable="moto_unplugged" />
	<item drawable="mytonwallet" />
	<item drawable="navegante" />
	<item drawable="nerv" />
	<item drawable="nmac_account_manager" />
	<item drawable="nodevideo" />
	<item drawable="noice_podcast_and_radio" />
	<item drawable="nothing_adaptive_icon_pack" />
	<item drawable="nothing_material_icon_pack" />
	<item drawable="nova_icon_pack_2" />
	<item drawable="nu_online" />
	<item drawable="nucleus_smart" />
	<item drawable="numberogram" />
	<item drawable="nyon_material_you_icons" />
	<item drawable="onsen" />
	<item drawable="oppo_community" />
	<item drawable="orange_business_lounge" />
	<item drawable="paidy" />
	<item drawable="pixel_studio" />
	<item drawable="polestar" />
	<item drawable="resona" />
	<item drawable="resona_group" />
	<item drawable="rush" />
	<item drawable="samsung_plus" />
	<item drawable="savefrom_helper" />
	<item drawable="screenshots" />
	<item drawable="serializd" />
	<item drawable="shizutools" />
	<item drawable="shuffles" />
	<item drawable="signal_detector" />
	<item drawable="sk_7mobile" />
	<item drawable="sketches" />
	<item drawable="sky_go" />
	<item drawable="sky_news" />
	<item drawable="sky_sports" />
	<item drawable="skype_for_business" />
	<item drawable="snitch" />
	<item drawable="sofabaton" />
	<item drawable="sort_collector" />
	<item drawable="spatial_touch" />
	<item drawable="squarespace" />
	<item drawable="stick_war_legacy" />
	<item drawable="suica_reader" />
	<item drawable="sunlight" />
	<item drawable="superset" />
	<item drawable="ten_ten" />
	<item drawable="time_recording_pro" />
	<item drawable="tips" />
	<item drawable="train_conductor_world" />
	<item drawable="trale" />
	<item drawable="tripletex" />
	<item drawable="tuta_mail" />
	<item drawable="uboi_vyom" />
	<item drawable="ul" />
	<item drawable="undertale" />
	<item drawable="v_point" />
	<item drawable="vibbo" />
	<item drawable="vmos" />
	<item drawable="we_care" />
	<item drawable="wearfit_pro" />
	<item drawable="wetv" />
	<item drawable="wifitransfer" />
	<item drawable="wifitransfer_alt" />
	<item drawable="workplace_chat" />
	<item drawable="xapk_installer" />
	<item drawable="y_yahoo" />
	<item drawable="yango" />
	<item drawable="yokai" />
	<item drawable="your_circle_icon_pack" />
	<item drawable="zeus_wallet" />
	<item drawable="zlantar" />
</resources>
